{
  "Ads":
  [
    {
      "select_main_ads": "ADMOB",
      "select_backup_ads":"APPLOVIN-D",
      "main_ads_banner": "ca-app-pub-1437241986629219/9766239847",
      "main_ads_intertitial":"ca-app-pub-1437241986629219/3200831491",
      "native_for_admob":"ca-app-pub-1437241986629219/8640416549",
      "backup_ads_banner":"b195f8dd8ded45fe847ad89ed1d016da",
      "backup_ads_intertitial":"b195f8dd8ded45fe847ad89ed1d016da",
      "interval_intertitial": 5,
      "initialize_sdk":"",
      "initialize_sdk_backup_ads":"",
      "high_paying_keyword_1": "",
      "high_paying_keyword_2": "",
      "high_paying_keyword_3": "",
      "high_paying_keyword_4": "",
      "high_paying_keyword_5": "",
      "status_app": "0",
      "link_redirect": "https://"
    }
  ],
  "Skin":
  [
   {
          "id":1,
          "name_skin":"FNAF",
          "skin_url":"https://aweu.net/2022/skinbee/FNAF/png/FNAF1.png",
          "view_skin":"https://aweu.net/2022/skinbee/FNAF/thumb/FNAF1.png"
          
          
        },
        {
          "id":2,
          "name_skin":"FNAF",
          "skin_url":"https://aweu.net/2022/skinbee/FNAF/png/FNAF2.png",
          "view_skin":"https://aweu.net/2022/skinbee/FNAF/thumb/FNAF2.png"
          
        },
        {
          "id":3,
          "name_skin":"FNAF",
          "skin_url":"https://aweu.net/2022/skinbee/FNAF/png/FNAF3.png",
          "view_skin":"https://aweu.net/2022/skinbee/FNAF/thumb/FNAF3.png"
          
          
        },
        {
          "id":4,
          "name_skin":"FNAF",
          "view_skin":"https://aweu.net/2022/skinbee/FNAF/thumb/FNAF4.png",
          "skin_url":"https://aweu.net/2022/skinbee/FNAF/png/FNAF4.png"
          
        },
        {
          "id":5,
          "name_skin":"FNAF",
          "skin_url":"https://aweu.net/2022/skinbee/FNAF/png/FNAF5.png",
          "view_skin":"https://aweu.net/2022/skinbee/FNAF/thumb/FNAF5.png"
          
          
        },
        {
          "id":6,
          "view_skin":"https://aweu.net/2022/skinbee/FNAF/thumb/FNAF6.png",
          "skin_url":"https://aweu.net/2022/skinbee/FNAF/png/FNAF6.png",
          "name_skin":"FNAF"
        },
        {
          "id":7,
          "view_skin":"https://aweu.net/2022/skinbee/FNAF/thumb/FNAF7.png",
          "skin_url":"https://aweu.net/2022/skinbee/FNAF/png/FNAF7.png",
          "name_skin":"FNAF"
        },
        {
          "id":8,
          "view_skin":"https://aweu.net/2022/skinbee/FNAF/thumb/FNAF8.png",
          "skin_url":"https://aweu.net/2022/skinbee/FNAF/png/FNAF8.png",
          "name_skin":"FNAF"
        },
        {
          "id":9,
          "view_skin":"https://aweu.net/2022/skinbee/FNAF/thumb/FNAF9.png",
          "skin_url":"https://aweu.net/2022/skinbee/FNAF/png/FNAF9.png",
          "name_skin":"FNAF"
        },
        {
          "id":10,
          "view_skin":"https://aweu.net/2022/skinbee/FNAF/thumb/FNAF10.png",
          "skin_url":"https://aweu.net/2022/skinbee/FNAF/png/FNAF10.png",
          "name_skin":"FNAF"
        },
        {
          "id":11,
          "view_skin":"https://aweu.net/2022/skinbee/FNAF/thumb/FNAF11.png",
          "skin_url":"https://aweu.net/2022/skinbee/FNAF/png/FNAF11.png",
          "name_skin":"FNAF"
        },
        {
          "id":12,
          "view_skin":"https://aweu.net/2022/skinbee/FNAF/thumb/FNAF12.png",
          "skin_url":"https://aweu.net/2022/skinbee/FNAF/png/FNAF12.png",
          "name_skin":"FNAF"
        },
        {
          "id":13,
          "view_skin":"https://aweu.net/2022/skinbee/FNAF/thumb/FNAF13.png",
          "skin_url":"https://aweu.net/2022/skinbee/FNAF/png/FNAF13.png",
          "name_skin":"FNAF"
        },
        {
          "id":14,
          "view_skin":"https://aweu.net/2022/skinbee/FNAF/thumb/FNAF14.png",
          "skin_url":"https://aweu.net/2022/skinbee/FNAF/png/FNAF14.png",
          "name_skin":"FNAF"
        },
        {
          "id":15,
          "view_skin":"https://aweu.net/2022/skinbee/FNAF/thumb/FNAF15.png",
          "skin_url":"https://aweu.net/2022/skinbee/FNAF/png/FNAF15.png",
          "name_skin":"FNAF"
        },
        {
          "id":16,
          "view_skin":"https://aweu.net/2022/skinbee/FNAF/thumb/FNAF16.png",
          "skin_url":"https://aweu.net/2022/skinbee/FNAF/png/FNAF16.png",
          "name_skin":"FNAF"
        },
        {
          "id":17,
          "view_skin":"https://aweu.net/2022/skinbee/FNAF/thumb/FNAF17.png",
          "skin_url":"https://aweu.net/2022/skinbee/FNAF/png/FNAF17.png",
          "name_skin":"FNAF"
        },
        {
          "id":18,
          "view_skin":"https://aweu.net/2022/skinbee/FNAF/thumb/FNAF18.png",
          "skin_url":"https://aweu.net/2022/skinbee/FNAF/png/FNAF18.png",
          "name_skin":"FNAF"
        },
        {
          "id":19,
          "view_skin":"https://aweu.net/2022/skinbee/FNAF/thumb/FNAF19.png",
          "skin_url":"https://aweu.net/2022/skinbee/FNAF/png/FNAF19.png",
          "name_skin":"FNAF"
        },
        {
          "id":20,
          "view_skin":"https://aweu.net/2022/skinbee/FNAF/thumb/FNAF20.png",
          "skin_url":"https://aweu.net/2022/skinbee/FNAF/png/FNAF20.png",
          "name_skin":"FNAF"
        },
        {
          "id":21,
          "view_skin":"https://aweu.net/2022/skinbee/FNAF/thumb/FNAF21.png",
          "skin_url":"https://aweu.net/2022/skinbee/FNAF/png/FNAF21.png",
          "name_skin":"FNAF"
        },
        {
          "id":22,
          "view_skin":"https://aweu.net/2022/skinbee/FNAF/thumb/FNAF22.png",
          "skin_url":"https://aweu.net/2022/skinbee/FNAF/png/FNAF22.png",
          "name_skin":"FNAF"
        },
        {
          "id":23,
          "view_skin":"https://aweu.net/2022/skinbee/FNAF/thumb/FNAF23.png",
          "skin_url":"https://aweu.net/2022/skinbee/FNAF/png/FNAF23.png",
          "name_skin":"FNAF"
        },
        {
          "id":24,
          "view_skin":"https://aweu.net/2022/skinbee/FNAF/thumb/FNAF24.png",
          "skin_url":"https://aweu.net/2022/skinbee/FNAF/png/FNAF24.png",
          "name_skin":"FNAF"
        },
        {
          "id":25,
          "view_skin":"https://aweu.net/2022/skinbee/FNAF/thumb/FNAF25.png",
          "skin_url":"https://aweu.net/2022/skinbee/FNAF/png/FNAF25.png",
          "name_skin":"FNAF"
        },
        {
          "id":26,
          "view_skin":"https://aweu.net/2022/skinbee/FNAF/thumb/FNAF26.png",
          "skin_url":"https://aweu.net/2022/skinbee/FNAF/png/FNAF26.png",
          "name_skin":"FNAF"
        },
        {
          "id":27,
          "view_skin":"https://aweu.net/2022/skinbee/FNAF/thumb/FNAF27.png",
          "skin_url":"https://aweu.net/2022/skinbee/FNAF/png/FNAF27.png",
          "name_skin":"FNAF"
        },
        {
          "id":28,
          "view_skin":"https://aweu.net/2022/skinbee/FNAF/thumb/FNAF28.png",
          "skin_url":"https://aweu.net/2022/skinbee/FNAF/png/FNAF28.png",
          "name_skin":"FNAF"
        },
        {
          "id":29,
          "view_skin":"https://aweu.net/2022/skinbee/FNAF/thumb/FNAF29.png",
          "skin_url":"https://aweu.net/2022/skinbee/FNAF/png/FNAF29.png",
          "name_skin":"FNAF"
        },
        {
          "id":30,
          "view_skin":"https://aweu.net/2022/skinbee/FNAF/thumb/FNAF30.png",
          "skin_url":"https://aweu.net/2022/skinbee/FNAF/png/FNAF30.png",
          "name_skin":"FNAF"
        },
        {
          "id":31,
          "view_skin":"https://aweu.net/2022/skinbee/FNAF/thumb/FNAF31.png",
          "skin_url":"https://aweu.net/2022/skinbee/FNAF/png/FNAF31.png",
          "name_skin":"FNAF"
        },
        {
          "id":32,
          "view_skin":"https://aweu.net/2022/skinbee/FNAF/thumb/FNAF32.png",
          "skin_url":"https://aweu.net/2022/skinbee/FNAF/png/FNAF32.png",
          "name_skin":"FNAF"
        },
        { 
          "id":33,
          "view_skin":"https://aweu.net/2022/skinbee/FNAF/thumb/FNAF33.png",
          "skin_url":"https://aweu.net/2022/skinbee/FNAF/png/FNAF33.png",
          "name_skin":"FNAF"
        },
        {
          "id":34,
          "view_skin":"https://aweu.net/2022/skinbee/FNAF/thumb/FNAF34.png",
          "skin_url":"https://aweu.net/2022/skinbee/FNAF/png/FNAF34.png",
          "name_skin":"FNAF"
        },
        {
          "id":35,
          "view_skin":"https://aweu.net/2022/skinbee/FNAF/thumb/FNAF35.png",
          "skin_url":"https://aweu.net/2022/skinbee/FNAF/png/FNAF35.png",
          "name_skin":"FNAF"
        },
        {
          "id":36,
          "view_skin":"https://aweu.net/2022/skinbee/FNAF/thumb/FNAF36.png",
          "skin_url":"https://aweu.net/2022/skinbee/FNAF/png/FNAF36.png",
          "name_skin":"FNAF"
        },
        {
          "id":37,
          "view_skin":"https://aweu.net/2022/skinbee/FNAF/thumb/FNAF37.png",
          "skin_url":"https://aweu.net/2022/skinbee/FNAF/png/FNAF37.png",
          "name_skin":"FNAF"
        },
        {
          "id":38,
          "view_skin":"https://aweu.net/2022/skinbee/FNAF/thumb/FNAF38.png",
          "skin_url":"https://aweu.net/2022/skinbee/FNAF/png/FNAF38.png",
          "name_skin":"FNAF"
        },
        {
          "id":39,
          "view_skin":"https://aweu.net/2022/skinbee/FNAF/thumb/FNAF39.png",
          "skin_url":"https://aweu.net/2022/skinbee/FNAF/png/FNAF39.png",
          "name_skin":"FNAF"
        },
        {
          "id":40,
          "view_skin":"https://aweu.net/2022/skinbee/FNAF/thumb/FNAF40.png",
          "skin_url":"https://aweu.net/2022/skinbee/FNAF/png/FNAF40.png",
          "name_skin":"FNAF"
        },
        {
          "id":41,
          "view_skin":"https://aweu.net/2022/skinbee/FNAF/thumb/FNAF41.png",
          "skin_url":"https://aweu.net/2022/skinbee/FNAF/png/FNAF41.png",
          "name_skin":"FNAF"
        },
        {
          "id":42,
          "view_skin":"https://aweu.net/2022/skinbee/FNAF/thumb/FNAF42.png",
          "skin_url":"https://aweu.net/2022/skinbee/FNAF/png/FNAF42.png",
          "name_skin":"FNAF"
        },
        {
          "id":43,
          "view_skin":"https://aweu.net/2022/skinbee/FNAF/thumb/FNAF43.png",
          "skin_url":"https://aweu.net/2022/skinbee/FNAF/png/FNAF43.png",
          "name_skin":"FNAF"
        },
        {
          "id":44,
          "view_skin":"https://aweu.net/2022/skinbee/FNAF/thumb/FNAF44.png",
          "skin_url":"https://aweu.net/2022/skinbee/FNAF/png/FNAF44.png",
          "name_skin":"FNAF"
        },
        {
          "id":45,
          "view_skin":"https://aweu.net/2022/skinbee/FNAF/thumb/FNAF45.png",
          "skin_url":"https://aweu.net/2022/skinbee/FNAF/png/FNAF45.png",
          "name_skin":"FNAF"
        },
        { 
          "id":46,
          "view_skin":"https://aweu.net/2022/skinbee/FNAF/thumb/FNAF46.png",
          "skin_url":"https://aweu.net/2022/skinbee/FNAF/png/FNAF46.png",
          "name_skin":"FNAF"
        },
        {
          "id":47,
          "view_skin":"https://aweu.net/2022/skinbee/FNAF/thumb/FNAF47.png",
          "skin_url":"https://aweu.net/2022/skinbee/FNAF/png/FNAF47.png",
          "name_skin":"FNAF"
        },
        {
          "id":48,
          "view_skin":"https://aweu.net/2022/skinbee/FNAF/thumb/FNAF48.png",
          "skin_url":"https://aweu.net/2022/skinbee/FNAF/png/FNAF48.png",
          "name_skin":"FNAF"
        },
        {
          "id":49,
          "view_skin":"https://aweu.net/2022/skinbee/FNAF/thumb/FNAF49.png",
          "skin_url":"https://aweu.net/2022/skinbee/FNAF/png/FNAF49.png",
          "name_skin":"FNAF"
        },
        {
          "id":50,
          "view_skin":"https://aweu.net/2022/skinbee/FNAF/thumb/FNAF50.png",
          "skin_url":"https://aweu.net/2022/skinbee/FNAF/png/FNAF50.png",
          "name_skin":"FNAF"
        },
        {
          "id":51,
          "view_skin":"https://aweu.net/2022/skinbee/FNAF/thumb/FNAF51.png",
          "skin_url":"https://aweu.net/2022/skinbee/FNAF/png/FNAF51.png",
          "name_skin":"FNAF"
        },
        {
          "id":52,
          "view_skin":"https://aweu.net/2022/skinbee/FNAF/thumb/FNAF52.png",
          "skin_url":"https://aweu.net/2022/skinbee/FNAF/png/FNAF52.png",
          "name_skin":"FNAF"
        },
        {
          "id":53,
          "view_skin":"https://aweu.net/2022/skinbee/FNAF/thumb/FNAF53.png",
          "skin_url":"https://aweu.net/2022/skinbee/FNAF/png/FNAF53.png",
          "name_skin":"FNAF"
        },
        {
          "id":54,
          "view_skin":"https://aweu.net/2022/skinbee/FNAF/thumb/FNAF54.png",
          "skin_url":"https://aweu.net/2022/skinbee/FNAF/png/FNAF54.png",
          "name_skin":"FNAF"
        },
        {
          "id":55,
          "view_skin":"https://aweu.net/2022/skinbee/FNAF/thumb/FNAF55.png",
          "skin_url":"https://aweu.net/2022/skinbee/FNAF/png/FNAF55.png",
          "name_skin":"FNAF"
        },
        {
          "id":56,
          "view_skin":"https://aweu.net/2022/skinbee/FNAF/thumb/FNAF56.png",
          "skin_url":"https://aweu.net/2022/skinbee/FNAF/png/FNAF56.png",
          "name_skin":"FNAF"
        },
        {
          "id":57,
          "view_skin":"https://aweu.net/2022/skinbee/FNAF/thumb/FNAF57.png",
          "skin_url":"https://aweu.net/2022/skinbee/FNAF/png/FNAF57.png",
         "name_skin":"FNAF"
        },
        {
          "id":58,
          "view_skin":"https://aweu.net/2022/skinbee/FNAF/thumb/FNAF58.png",
          "skin_url":"https://aweu.net/2022/skinbee/FNAF/png/FNAF58.png",
          "name_skin":"FNAF"
        },
        {
          "id":59,
          "view_skin":"https://aweu.net/2022/skinbee/FNAF/thumb/FNAF59.png",
          "skin_url":"https://aweu.net/2022/skinbee/FNAF/png/FNAF59.png",
          "name_skin":"FNAF"
        },
        {
          "id":60,
          "view_skin":"https://aweu.net/2022/skinbee/FNAF/thumb/FNAF60.png",
          "skin_url":"https://aweu.net/2022/skinbee/FNAF/png/FNAF60.png",
          "name_skin":"FNAF"
        },
        {
          "id":61,
          "view_skin":"https://aweu.net/2022/skinbee/FNAF/thumb/FNAF61.png",
          "skin_url":"https://aweu.net/2022/skinbee/FNAF/png/FNAF61.png",
          "name_skin":"FNAF"
        },
        {
          "id":62,
          "view_skin":"https://aweu.net/2022/skinbee/FNAF/thumb/FNAF62.png",
          "skin_url":"https://aweu.net/2022/skinbee/FNAF/png/FNAF62.png",
          "name_skin":"FNAF"
        },
        {
          "id":63,
          "view_skin":"https://aweu.net/2022/skinbee/FNAF/thumb/FNAF63.png",
          "skin_url":"https://aweu.net/2022/skinbee/FNAF/png/FNAF63.png",
          "name_skin":"FNAF"
        },
        {
          "id":64,
          "view_skin":"https://aweu.net/2022/skinbee/FNAF/thumb/FNAF64.png",
          "skin_url":"https://aweu.net/2022/skinbee/FNAF/png/FNAF64.png",
          "name_skin":"FNAF"
        },
        {
          "id":65,
          "view_skin":"https://aweu.net/2022/skinbee/FNAF/thumb/FNAF65.png",
          "skin_url":"https://aweu.net/2022/skinbee/FNAF/png/FNAF65.png",
          "name_skin":"FNAF"
        },
        {
          "id":66,
          "view_skin":"https://aweu.net/2022/skinbee/FNAF/thumb/FNAF66.png",
          "skin_url":"https://aweu.net/2022/skinbee/FNAF/png/FNAF66.png",
          "name_skin":"FNAF"
        },
        {
          "id":67,
          "view_skin":"https://aweu.net/2022/skinbee/FNAF/thumb/FNAF67.png",
          "skin_url":"https://aweu.net/2022/skinbee/FNAF/png/FNAF67.png",
          "name_skin":"FNAF"
        },
        {
          "id":68,
          "view_skin":"https://aweu.net/2022/skinbee/FNAF/thumb/FNAF68.png",
          "skin_url":"https://aweu.net/2022/skinbee/FNAF/png/FNAF68.png",
          "name_skin":"FNAF"
        },
        {
          "id":69,
          "view_skin":"https://aweu.net/2022/skinbee/FNAF/thumb/FNAF69.png",
          "skin_url":"https://aweu.net/2022/skinbee/FNAF/png/FNAF69.png",
          "name_skin":"FNAF"
        },
        {
          "id":70,
          "view_skin":"https://aweu.net/2022/skinbee/FNAF/thumb/FNAF70.png",
          "skin_url":"https://aweu.net/2022/skinbee/FNAF/png/FNAF70.png",
          "name_skin":"FNAF"
        },
        {
          "id":71,
          "view_skin":"https://aweu.net/2022/skinbee/FNAF/thumb/FNAF71.png",
          "skin_url":"https://aweu.net/2022/skinbee/FNAF/png/FNAF71.png",
          "name_skin":"FNAF"
        },
        {
          "id":72,
          "view_skin":"https://aweu.net/2022/skinbee/FNAF/thumb/FNAF72.png",
          "skin_url":"https://aweu.net/2022/skinbee/FNAF/png/FNAF72.png",
          "name_skin":"FNAF"
        },
        {
          "id":73,
          "view_skin":"https://aweu.net/2022/skinbee/FNAF/thumb/FNAF73.png",
          "skin_url":"https://aweu.net/2022/skinbee/FNAF/png/FNAF73.png",
          "name_skin":"FNAF"
        },
        {
          "id":74,
          "view_skin":"https://aweu.net/2022/skinbee/FNAF/thumb/FNAF74.png",
          "skin_url":"https://aweu.net/2022/skinbee/FNAF/png/FNAF74.png",
          "name_skin":"FNAF"
        },
        {
          "id":75,
          "view_skin":"https://aweu.net/2022/skinbee/FNAF/thumb/FNAF75.png",
          "skin_url":"https://aweu.net/2022/skinbee/FNAF/png/FNAF75.png",
          "name_skin":"FNAF"
        },
        {
          "id":76,
          "view_skin":"https://aweu.net/2022/skinbee/FNAF/thumb/FNAF76.png",
          "skin_url":"https://aweu.net/2022/skinbee/FNAF/png/FNAF76.png",
          "name_skin":"FNAF"
        },
        {
          "id":77,
          "view_skin":"https://aweu.net/2022/skinbee/FNAF/thumb/FNAF77.png",
          "skin_url":"https://aweu.net/2022/skinbee/FNAF/png/FNAF77.png",
          "name_skin":"FNAF"
        },
        {
          "id":78,
          "view_skin":"https://aweu.net/2022/skinbee/FNAF/thumb/FNAF78.png",
          "skin_url":"https://aweu.net/2022/skinbee/FNAF/png/FNAF78.png",
          "name_skin":"FNAF"
        },
        {
          "id":79,
          "view_skin":"https://aweu.net/2022/skinbee/FNAF/thumb/FNAF79.png",
          "skin_url":"https://aweu.net/2022/skinbee/FNAF/png/FNAF79.png",
          "name_skin":"FNAF"
        },
        {
          "id":80,
          "view_skin":"https://aweu.net/2022/skinbee/FNAF/thumb/FNAF80.png",
          "skin_url":"https://aweu.net/2022/skinbee/FNAF/png/FNAF80.png",
          "name_skin":"FNAF"
        },
        {
          "id":81,
          "view_skin":"https://aweu.net/2022/skinbee/FNAF/thumb/FNAF81.png",
          "skin_url":"https://aweu.net/2022/skinbee/FNAF/png/FNAF81.png",
          "name_skin":"FNAF"
        },
        {
          "id":82,
          "view_skin":"https://aweu.net/2022/skinbee/FNAF/thumb/FNAF82.png",
          "skin_url":"https://aweu.net/2022/skinbee/FNAF/png/FNAF82.png",
          "name_skin":"FNAF"
        },
        {
          "id":83,
          "view_skin":"https://aweu.net/2022/skinbee/FNAF/thumb/FNAF83.png",
          "skin_url":"https://aweu.net/2022/skinbee/FNAF/png/FNAF83.png",
          "name_skin":"FNAF"
        },
        {
          "id":84,
          "view_skin":"https://aweu.net/2022/skinbee/FNAF/thumb/FNAF84.png",
          "skin_url":"https://aweu.net/2022/skinbee/FNAF/png/FNAF84.png",
          "name_skin":"FNAF"
        },
        {
          "id":85,
          "view_skin":"https://aweu.net/2022/skinbee/FNAF/thumb/FNAF85.png",
          "skin_url":"https://aweu.net/2022/skinbee/FNAF/png/FNAF85.png",
          "name_skin":"FNAF"
        },
        {
          "id":86,
          "view_skin":"https://aweu.net/2022/skinbee/FNAF/thumb/FNAF86.png",
          "skin_url":"https://aweu.net/2022/skinbee/FNAF/png/FNAF86.png",
          "name_skin":"FNAF"
        },
        {
          "id":87,
          "view_skin":"https://aweu.net/2022/skinbee/FNAF/thumb/FNAF87.png",
          "skin_url":"https://aweu.net/2022/skinbee/FNAF/png/FNAF87.png",
          "name_skin":"FNAF"
        },
        {
          "id":88,
          "view_skin":"https://aweu.net/2022/skinbee/FNAF/thumb/FNAF88.png",
          "skin_url":"https://aweu.net/2022/skinbee/FNAF/png/FNAF88.png",
         "name_skin":"FNAF"
        },
        {
          "id":89,
          "view_skin":"https://aweu.net/2022/skinbee/FNAF/thumb/FNAF89.png",
          "skin_url":"https://aweu.net/2022/skinbee/FNAF/png/FNAF89.png",
          "name_skin":"FNAF"
        }
        ,
        {
          "id":90,
          "view_skin":"https://aweu.net/2022/skinbee/FNAF/thumb/FNAF90.png",
          "skin_url":"https://aweu.net/2022/skinbee/FNAF/png/FNAF90.png",
          "name_skin":"FNAF"
        }
        ,
        {
          "id":91,
          "view_skin":"https://aweu.net/2022/skinbee/FNAF/thumb/FNAF91.png",
          "skin_url":"https://aweu.net/2022/skinbee/FNAF/png/FNAF91.png",
          "name_skin":"FNAF"
        }
        ,
        {
          "id":92,
          "view_skin":"https://aweu.net/2022/skinbee/FNAF/thumb/FNAF92.png",
          "skin_url":"https://aweu.net/2022/skinbee/FNAF/png/FNAF92.png",
          "name_skin":"FNAF"
        }
        ,
        {
          "id":93,
          "view_skin":"https://aweu.net/2022/skinbee/FNAF/thumb/FNAF93.png",
          "skin_url":"https://aweu.net/2022/skinbee/FNAF/png/FNAF93.png",
          "name_skin":"FNAF"
        }
        ,
        {
          "id":94,
          "view_skin":"https://aweu.net/2022/skinbee/FNAF/thumb/FNAF94.png",
          "skin_url":"https://aweu.net/2022/skinbee/FNAF/png/FNAF94.png",
          "name_skin":"FNAF"
        }
        ,
        {
          "id":95,
          "view_skin":"https://aweu.net/2022/skinbee/FNAF/thumb/FNAF95.png",
          "skin_url":"https://aweu.net/2022/skinbee/FNAF/png/FNAF95.png",
          "name_skin":"FNAF"
        }
        ,
        {
          "id":96,
          "view_skin":"https://aweu.net/2022/skinbee/FNAF/thumb/FNAF96.png",
          "skin_url":"https://aweu.net/2022/skinbee/FNAF/png/FNAF96.png",
         "name_skin":"FNAF"
        }
        ,
        {
          "id":97,
          "view_skin":"https://aweu.net/2022/skinbee/FNAF/thumb/FNAF97.png",
          "skin_url":"https://aweu.net/2022/skinbee/FNAF/png/FNAF97.png",
          "name_skin":"FNAF"
        }
        ,
        {
          "id":98,
          "view_skin":"https://aweu.net/2022/skinbee/FNAF/thumb/FNAF98.png",
          "skin_url":"https://aweu.net/2022/skinbee/FNAF/png/FNAF98.png",
          "name_skin":"FNAF"
        }
        ,
        {
          "id":99,
          "view_skin":"https://aweu.net/2022/skinbee/FNAF/thumb/FNAF99.png",
          "skin_url":"https://aweu.net/2022/skinbee/FNAF/png/FNAF99.png",
          "name_skin":"FNAF"
        }
        ,
        {
          "id":100,
          "view_skin":"https://aweu.net/2022/skinbee/FNAF/thumb/FNAF100.png",
          "skin_url":"https://aweu.net/2022/skinbee/FNAF/png/FNAF100.png",
          "name_skin":"FNAF"
        }
        ,
        {
          "id":101,
          "view_skin":"https://aweu.net/2022/skinbee/FNAF/thumb/FNAF101.png",
          "skin_url":"https://aweu.net/2022/skinbee/FNAF/png/FNAF101.png",
          "name_skin":"FNAF"
        }
        ,
        {
          "id":102,
          "view_skin":"https://aweu.net/2022/skinbee/FNAF/thumb/FNAF102.png",
          "skin_url":"https://aweu.net/2022/skinbee/FNAF/png/FNAF102.png",
          "name_skin":"FNAF"
        }
        ,
        {
          "id":103,
          "view_skin":"https://aweu.net/2022/skinbee/FNAF/thumb/FNAF103.png",
          "skin_url":"https://aweu.net/2022/skinbee/FNAF/png/FNAF103.png",
          "name_skin":"FNAF"
        }
        ,
        {
          "id":104,
          "view_skin":"https://aweu.net/2022/skinbee/FNAF/thumb/FNAF104.png",
          "skin_url":"https://aweu.net/2022/skinbee/FNAF/png/FNAF104.png",
          "name_skin":"FNAF"
        }
        ,
        {
          "id":105,
          "view_skin":"https://aweu.net/2022/skinbee/FNAF/thumb/FNAF105.png",
          "skin_url":"https://aweu.net/2022/skinbee/FNAF/png/FNAF105.png",
          "name_skin":"FNAF"
        }
        ,
        {
          "id":106,
          "view_skin":"https://aweu.net/2022/skinbee/FNAF/thumb/FNAF106.png",
          "skin_url":"https://aweu.net/2022/skinbee/FNAF/png/FNAF106.png",
          "name_skin":"FNAF"
        }
        ,
        {
          "id":107,
          "view_skin":"https://aweu.net/2022/skinbee/FNAF/thumb/FNAF107.png",
          "skin_url":"https://aweu.net/2022/skinbee/FNAF/png/FNAF107.png",
          "name_skin":"FNAF"
        }
        ,
        {
          "id":108,
          "view_skin":"https://aweu.net/2022/skinbee/FNAF/thumb/FNAF108.png",
          "skin_url":"https://aweu.net/2022/skinbee/FNAF/png/FNAF108.png",
          "name_skin":"FNAF"
        }
        ,
        {
          "id":109,
          "view_skin":"https://aweu.net/2022/skinbee/FNAF/thumb/FNAF109.png",
          "skin_url":"https://aweu.net/2022/skinbee/FNAF/png/FNAF109.png",
          "name_skin":"FNAF"
        }
        ,
        {
          "id":110,
          "view_skin":"https://aweu.net/2022/skinbee/FNAF/thumb/FNAF110.png",
          "skin_url":"https://aweu.net/2022/skinbee/FNAF/png/FNAF110.png",
          "name_skin":"FNAF"
        }
        ,
        {
          "id":111,
          "view_skin":"https://aweu.net/2022/skinbee/FNAF/thumb/FNAF111.png",
          "skin_url":"https://aweu.net/2022/skinbee/FNAF/png/FNAF111.png",
          "name_skin":"FNAF"
        }
        ,
        {
          "id":112,
          "view_skin":"https://aweu.net/2022/skinbee/FNAF/thumb/FNAF112.png",
          "skin_url":"https://aweu.net/2022/skinbee/FNAF/png/FNAF112.png",
          "name_skin":"FNAF"
        }
        ,
        {
          "id":113,
          "view_skin":"https://aweu.net/2022/skinbee/FNAF/thumb/FNAF113.png",
          "skin_url":"https://aweu.net/2022/skinbee/FNAF/png/FNAF113.png",
          "name_skin":"FNAF"
        }
        ,
        {
          "id":114,
          "view_skin":"https://aweu.net/2022/skinbee/FNAF/thumb/FNAF114.png",
          "skin_url":"https://aweu.net/2022/skinbee/FNAF/png/FNAF114.png",
          "name_skin":"FNAF"
        }
        ,
        {
          "id":115,
          "view_skin":"https://aweu.net/2022/skinbee/FNAF/thumb/FNAF115.png",
          "skin_url":"https://aweu.net/2022/skinbee/FNAF/png/FNAF115.png",
          "name_skin":"FNAF"
        }
        ,
        {
          "id":116,
          "view_skin":"https://aweu.net/2022/skinbee/FNAF/thumb/FNAF116.png",
          "skin_url":"https://aweu.net/2022/skinbee/FNAF/png/FNAF116.png",
          "name_skin":"FNAF"
        }

        ,
        {
          "id":117,
          "view_skin":"https://aweu.net/2022/skinbee/FNAF/thumb/FNAF117.png",
          "skin_url":"https://aweu.net/2022/skinbee/FNAF/png/FNAF117.png",
          "name_skin":"FNAF"
        }
        ,
        {
          "id":118,
          "view_skin":"https://aweu.net/2022/skinbee/FNAF/thumb/FNAF118.png",
          "skin_url":"https://aweu.net/2022/skinbee/FNAF/png/FNAF118.png",
          "name_skin":"FNAF"
        }
        ,
        {
          "id":119,
          "view_skin":"https://aweu.net/2022/skinbee/FNAF/thumb/FNAF119.png",
          "skin_url":"https://aweu.net/2022/skinbee/FNAF/png/FNAF119.png",
          "name_skin":"FNAF"
        }
        ,
        {
          "id":120,
          "view_skin":"https://aweu.net/2022/skinbee/FNAF/thumb/FNAF120.png",
          "skin_url":"https://aweu.net/2022/skinbee/FNAF/png/FNAF120.png",
          "name_skin":"FNAF"
        }
        ,
        {
          "id":121,
          "view_skin":"https://aweu.net/2022/skinbee/FNAF/thumb/FNAF121.png",
          "skin_url":"https://aweu.net/2022/skinbee/FNAF/png/FNAF121.png",
          "name_skin":"FNAF"
        }
        ,
        {
          "id":122,
          "view_skin":"https://aweu.net/2022/skinbee/FNAF/thumb/FNAF122.png",
          "skin_url":"https://aweu.net/2022/skinbee/FNAF/png/FNAF122.png",
          "name_skin":"FNAF"
        }
        ,
        {
          "id":123,
          "view_skin":"https://aweu.net/2022/skinbee/FNAF/thumb/FNAF123.png",
          "skin_url":"https://aweu.net/2022/skinbee/FNAF/png/FNAF123.png",
          "name_skin":"FNAF"
        }
        ,
        {
          "id":124,
          "view_skin":"https://aweu.net/2022/skinbee/FNAF/thumb/FNAF124.png",
          "skin_url":"https://aweu.net/2022/skinbee/FNAF/png/FNAF124.png",
          "name_skin":"FNAF"
        }
        ,
        {
          "id":125,
          "view_skin":"https://aweu.net/2022/skinbee/FNAF/thumb/FNAF125.png",
          "skin_url":"https://aweu.net/2022/skinbee/FNAF/png/FNAF125.png",
          "name_skin":"FNAF"
        }
        ,
        {
          "id":126,
          "view_skin":"https://aweu.net/2022/skinbee/FNAF/thumb/FNAF126.png",
          "skin_url":"https://aweu.net/2022/skinbee/FNAF/png/FNAF126.png",
          "name_skin":"FNAF"
        }
        ,
        {
          "id":127,
          "view_skin":"https://aweu.net/2022/skinbee/FNAF/thumb/FNAF127.png",
          "skin_url":"https://aweu.net/2022/skinbee/FNAF/png/FNAF127.png",
          "name_skin":"FNAF"
        }
        ,
        {
          "id":128,
          "view_skin":"https://aweu.net/2022/skinbee/FNAF/thumb/FNAF128.png",
          "skin_url":"https://aweu.net/2022/skinbee/FNAF/png/FNAF128.png",
          "name_skin":"FNAF"
        }
        ,
        {
          "id":129,
          "view_skin":"https://aweu.net/2022/skinbee/FNAF/thumb/FNAF129.png",
          "skin_url":"https://aweu.net/2022/skinbee/FNAF/png/FNAF129.png",
          "name_skin":"FNAF"
        }
        ,
        {
          "id":130,
          "view_skin":"https://aweu.net/2022/skinbee/FNAF/thumb/FNAF130.png",
          "skin_url":"https://aweu.net/2022/skinbee/FNAF/png/FNAF130.png",
          "name_skin":"FNAF"
        }
        ,
        {
          "id":131,
          "view_skin":"https://aweu.net/2022/skinbee/FNAF/thumb/FNAF131.png",
          "skin_url":"https://aweu.net/2022/skinbee/FNAF/png/FNAF131.png",
          "name_skin":"FNAF"
        }
        ,
        {
          "id":132,
          "view_skin":"https://aweu.net/2022/skinbee/FNAF/thumb/FNAF132.png",
          "skin_url":"https://aweu.net/2022/skinbee/FNAF/png/FNAF132.png",
          "name_skin":"FNAF"
        }
        ,
        {
          "id":133,
          "view_skin":"https://aweu.net/2022/skinbee/FNAF/thumb/FNAF133.png",
          "skin_url":"https://aweu.net/2022/skinbee/FNAF/png/FNAF133.png",
          "name_skin":"FNAF"
        }
        ,
        {
          "id":134,
          "view_skin":"https://aweu.net/2022/skinbee/FNAF/thumb/FNAF134.png",
          "skin_url":"https://aweu.net/2022/skinbee/FNAF/png/FNAF134.png",
          "name_skin":"FNAF"
        }
        ,
        {
          "id":135,
          "view_skin":"https://aweu.net/2022/skinbee/FNAF/thumb/FNAF135.png",
          "skin_url":"https://aweu.net/2022/skinbee/FNAF/png/FNAF135.png",
          "name_skin":"FNAF"
        }
        ,
        {
          "id":136,
          "view_skin":"https://aweu.net/2022/skinbee/FNAF/thumb/FNAF136.png",
          "skin_url":"https://aweu.net/2022/skinbee/FNAF/png/FNAF136.png",
          "name_skin":"FNAF"
        }
        ,
        {
          "id":137,
          "view_skin":"https://aweu.net/2022/skinbee/FNAF/thumb/FNAF137.png",
          "skin_url":"https://aweu.net/2022/skinbee/FNAF/png/FNAF137.png",
          "name_skin":"FNAF"
        }
        ,
        {
          "id":138,
          "view_skin":"https://aweu.net/2022/skinbee/FNAF/thumb/FNAF138.png",
          "skin_url":"https://aweu.net/2022/skinbee/FNAF/png/FNAF138.png",
          "name_skin":"FNAF"
        }
        ,
        {
          "id":139,
          "view_skin":"https://aweu.net/2022/skinbee/FNAF/thumb/FNAF139.png",
          "skin_url":"https://aweu.net/2022/skinbee/FNAF/png/FNAF139.png",
          "name_skin":"FNAF"
        }
        ,
        {
          "id":140,
          "view_skin":"https://aweu.net/2022/skinbee/FNAF/thumb/FNAF140.png",
          "skin_url":"https://aweu.net/2022/skinbee/FNAF/png/FNAF140.png",
          "name_skin":"FNAF"
        }
        ,
        {
          "id":141,
          "view_skin":"https://aweu.net/2022/skinbee/FNAF/thumb/FNAF141.png",
          "skin_url":"https://aweu.net/2022/skinbee/FNAF/png/FNAF141.png",
          "name_skin":"FNAF"
        }
        ,
        {
          "id":142,
          "view_skin":"https://aweu.net/2022/skinbee/FNAF/thumb/FNAF142.png",
          "skin_url":"https://aweu.net/2022/skinbee/FNAF/png/FNAF142.png",
          "name_skin":"FNAF"
        }
        ,
        {
          "id":143,
          "view_skin":"https://aweu.net/2022/skinbee/FNAF/thumb/FNAF143.png",
          "skin_url":"https://aweu.net/2022/skinbee/FNAF/png/FNAF143.png",
          "name_skin":"FNAF"
        }
        ,
        {
          "id":145,
          "view_skin":"https://aweu.net/2022/skinbee/FNAF/thumb/FNAF145.png",
          "skin_url":"https://aweu.net/2022/skinbee/FNAF/png/FNAF145.png",
          "name_skin":"FNAF"
        }
        ,
        {
          "id":146,
          "view_skin":"https://aweu.net/2022/skinbee/FNAF/thumb/FNAF146.png",
          "skin_url":"https://aweu.net/2022/skinbee/FNAF/png/FNAF146.png",
          "name_skin":"FNAF"
        }
        ,
        {
          "id":147,
          "view_skin":"https://aweu.net/2022/skinbee/FNAF/thumb/FNAF147.png",
          "skin_url":"https://aweu.net/2022/skinbee/FNAF/png/FNAF147.png",
          "name_skin":"FNAF"
        }
        ,
        {
          "id":148,
          "view_skin":"https://aweu.net/2022/skinbee/FNAF/thumb/FNAF148.png",
          "skin_url":"https://aweu.net/2022/skinbee/FNAF/png/FNAF148.png",
          "name_skin":"FNAF"
        }
        ,
        {
          "id":149,
          "view_skin":"https://aweu.net/2022/skinbee/FNAF/thumb/FNAF149.png",
          "skin_url":"https://aweu.net/2022/skinbee/FNAF/png/FNAF149.png",
          "name_skin":"FNAF"
        }
        ,
        {
          "id":150,
          "view_skin":"https://aweu.net/2022/skinbee/FNAF/thumb/FNAF150.png",
          "skin_url":"https://aweu.net/2022/skinbee/FNAF/png/FNAF150.png",
          "name_skin":"FNAF"
        }
        ,
        {
          "id":151,
          "view_skin":"https://aweu.net/2022/skinbee/FNAF/thumb/FNAF151.png",
          "skin_url":"https://aweu.net/2022/skinbee/FNAF/png/FNAF151.png",
          "name_skin":"FNAF"
        }
        ,
        {
          "id":152,
          "view_skin":"https://aweu.net/2022/skinbee/FNAF/thumb/FNAF152.png",
          "skin_url":"https://aweu.net/2022/skinbee/FNAF/png/FNAF152.png",
          "name_skin":"FNAF"
        }
        ,
        {
          "id":153,
          "view_skin":"https://aweu.net/2022/skinbee/FNAF/thumb/FNAF153.png",
          "skin_url":"https://aweu.net/2022/skinbee/FNAF/png/FNAF153.png",
          "name_skin":"FNAF"
        }
        ,
        {
          "id":154,
          "view_skin":"https://aweu.net/2022/skinbee/FNAF/thumb/FNAF154.png",
          "skin_url":"https://aweu.net/2022/skinbee/FNAF/png/FNAF154.png",
          "name_skin":"FNAF"
        }
        ,
        {
          "id":155,
          "view_skin":"https://aweu.net/2022/skinbee/FNAF/thumb/FNAF155.png",
          "skin_url":"https://aweu.net/2022/skinbee/FNAF/png/FNAF155.png",
          "name_skin":"FNAF"
        }
     
       

  ]
}

